vartracer/ASTParser.py
vartracer/Utilities.py
vartracer/VarTracer_Core.py
vartracer/__init__.py
vartracer/test_code/__init__.py
vartracer/test_code/playground.py
vartracer/test_code/playground_2.py
vartracer/test_code/recurse.py
vartracer/trace_output/VTrace_exec_stack.json
vartracer/trace_output/VTrace_exec_stack.txt
vartracer/trace_output/VTrace_raw_output.txt
vartracer-0.1.2.dist-info/METADATA
vartracer-0.1.2.dist-info/WHEEL
vartracer-0.1.2.dist-info/RECORD
