Metadata-Version: 2.3
Name: VarTracer
Version: 0.1.2
Summary: A Python tool for tracing and analyzing code execution.
License: MIT
Keywords: tracing,debugging,analysis,python
Author: Mengqi Zhang
Author-email: jiujiuchangshou@gmail.com
Requires-Python: >=3.8,<4.0
Classifier: License :: OSI Approved :: MIT License
Classifier: Programming Language :: Python :: 3
Classifier: Programming Language :: Python :: 3.8
Classifier: Programming Language :: Python :: 3.9
Classifier: Programming Language :: Python :: 3.10
Classifier: Programming Language :: Python :: 3.11
Classifier: Programming Language :: Python :: 3.12
Classifier: Programming Language :: Python :: 3.13
Project-URL: Homepage, https://github.com/jiujiucs17/VarTracer
Project-URL: Repository, https://github.com/jiujiucs17/VarTracer
